generala/__init__.py
generala/__main__.py
generala/categories.py
generala-2.0.0.dist-info/LICENSE.txt
generala-2.0.0.dist-info/METADATA
generala-2.0.0.dist-info/WHEEL
generala-2.0.0.dist-info/entry_points.txt
generala-2.0.0.dist-info/top_level.txt
generala-2.0.0.dist-info/RECORD
