Metadata-Version: 2.1
Name: generala
Version: 2.0.0
Summary: Maximize your score in a turn of the Generala dice game
Author: Gabriel Gerlero
Project-URL: Homepage, https://github.com/gerlero/generala
Project-URL: Repository, https://github.com/gerlero/generala
Classifier: Development Status :: 5 - Production/Stable
Classifier: Intended Audience :: Developers
Classifier: Intended Audience :: Education
Classifier: Intended Audience :: End Users/Desktop
Classifier: License :: OSI Approved :: MIT License
Classifier: Programming Language :: Python
Classifier: Programming Language :: Python :: 3
Classifier: Programming Language :: Python :: 3.9
Classifier: Programming Language :: Python :: 3.10
Classifier: Programming Language :: Python :: 3.11
Classifier: Programming Language :: Python :: 3.12
Classifier: Programming Language :: Python :: 3.13
Classifier: Topic :: Games/Entertainment
Classifier: Topic :: Software Development :: Libraries
Classifier: Operating System :: OS Independent
Requires-Python: >=3.9
License-File: LICENSE.txt
Requires-Dist: numpy<3,>=1
Provides-Extra: lint
Requires-Dist: ruff; extra == "lint"
